bids2cite/__init__.py
bids2cite/_version.py
bids2cite/authors.py
bids2cite/bids2cite.py
bids2cite/license.py
bids2cite/references.py
bids2cite/utils.py
bids2cite-0.1.1.dist-info/LICENSE
bids2cite-0.1.1.dist-info/METADATA
bids2cite-0.1.1.dist-info/WHEEL
bids2cite-0.1.1.dist-info/entry_points.txt
bids2cite-0.1.1.dist-info/top_level.txt
bids2cite-0.1.1.dist-info/RECORD
