Metadata-Version: 2.1
Name: bids2cite
Version: 0.1.1
Summary: create a citation file for a BIDS dataset
Home-page: https://github.com/Remi-Gau/bids2cite
Download-URL: https://github.com/Remi-Gau/bids2cite
Author: Remi Gau
Maintainer: Remi Gau
Maintainer-email: remi.gau@gmail.com
License: LGPL-3.0
Keywords: BIDS,datacite
Platform: OS Independent
Classifier: Development Status :: 3 - Alpha
Classifier: Intended Audience :: Science/Research
Classifier: License :: OSI Approved :: GNU Lesser General Public License v3 (LGPLv3)
Classifier: Programming Language :: Python
Classifier: Programming Language :: Python :: 3
Provides: bids2cite
License-File: LICENSE
Requires-Dist: rich
Requires-Dist: ruamel.yaml
Requires-Dist: black
Requires-Dist: requests
Requires-Dist: isort
Requires-Dist: crossref-commons
Requires-Dist: pandas
Provides-Extra: dev
Requires-Dist: sphinx (>=2.0) ; extra == 'dev'
Requires-Dist: sphinx-argparse ; extra == 'dev'
Requires-Dist: sphinx-rtd-theme ; extra == 'dev'
Requires-Dist: sphinx-copybutton ; extra == 'dev'
Requires-Dist: myst-parser ; extra == 'dev'
Requires-Dist: rstcheck ; extra == 'dev'
Requires-Dist: flake8 (>=3.7) ; extra == 'dev'
Requires-Dist: flake8-docstrings (>=1.5) ; extra == 'dev'
Requires-Dist: black (>=21) ; extra == 'dev'
Requires-Dist: pre-commit ; extra == 'dev'
Requires-Dist: sourcery ; extra == 'dev'
Requires-Dist: mypy ; extra == 'dev'
Requires-Dist: types-requests ; extra == 'dev'
Requires-Dist: pytest (>=6.2.5) ; extra == 'dev'
Requires-Dist: pytest-cov ; extra == 'dev'
Requires-Dist: coverage ; extra == 'dev'
Provides-Extra: doc
Requires-Dist: sphinx (>=2.0) ; extra == 'doc'
Requires-Dist: sphinx-argparse ; extra == 'doc'
Requires-Dist: sphinx-rtd-theme ; extra == 'doc'
Requires-Dist: sphinx-copybutton ; extra == 'doc'
Requires-Dist: myst-parser ; extra == 'doc'
Requires-Dist: rstcheck ; extra == 'doc'
Provides-Extra: docs
Requires-Dist: sphinx (>=2.0) ; extra == 'docs'
Requires-Dist: sphinx-argparse ; extra == 'docs'
Requires-Dist: sphinx-rtd-theme ; extra == 'docs'
Requires-Dist: sphinx-copybutton ; extra == 'docs'
Requires-Dist: myst-parser ; extra == 'docs'
Requires-Dist: rstcheck ; extra == 'docs'
Provides-Extra: style
Requires-Dist: flake8 (>=3.7) ; extra == 'style'
Requires-Dist: flake8-docstrings (>=1.5) ; extra == 'style'
Requires-Dist: black (>=21) ; extra == 'style'
Requires-Dist: pre-commit ; extra == 'style'
Requires-Dist: sourcery ; extra == 'style'
Requires-Dist: mypy ; extra == 'style'
Requires-Dist: types-requests ; extra == 'style'
Provides-Extra: test
Requires-Dist: pytest (>=6.2.5) ; extra == 'test'
Requires-Dist: pytest-cov ; extra == 'test'
Requires-Dist: coverage ; extra == 'test'
Provides-Extra: tests
Requires-Dist: pytest (>=6.2.5) ; extra == 'tests'
Requires-Dist: pytest-cov ; extra == 'tests'
Requires-Dist: coverage ; extra == 'tests'
